dataprobe/__init__.py
dataprobe/debugger/__init__.py
dataprobe/debugger/pipeline_debugger.py
dataprobe/utils/__init__.py
dataprobe/utils/helpers.py
dataprobe/utils/logger.py
dataprobe/validators/__init__.py
dataprobe/validators/smart_schema.py
dataprobe-2.1.0.dist-info/licenses/LICENSE
dataprobe-2.1.0.dist-info/METADATA
dataprobe-2.1.0.dist-info/WHEEL
dataprobe-2.1.0.dist-info/entry_points.txt
dataprobe-2.1.0.dist-info/top_level.txt
dataprobe-2.1.0.dist-info/RECORD
